af_metrics/__init__.py
af_metrics/monitoring_module.py
af_metrics-0.0.0.dist-info/LICENSE
af_metrics-0.0.0.dist-info/METADATA
af_metrics-0.0.0.dist-info/WHEEL
af_metrics-0.0.0.dist-info/top_level.txt
af_metrics-0.0.0.dist-info/RECORD
