Metadata-Version: 2.1
Name: af-metrics
Version: 0.0.0
Summary: A Python package for monitoring the Coffea Casa Analysis Facility
Author: Durbar Chakraborty
Author-email: durbardibyo@gmail.com
License-File: LICENSE
Requires-Dist: prometheus-client (>=0.14.1)
